audioanalyser/__init__.py
audioanalyser/__main__.py
audioanalyser/modules/__init__.py
audioanalyser/modules/analyze_text_files.py
audioanalyser/modules/audio_recorder.py
audioanalyser/modules/azure_recommendation.py
audioanalyser/modules/azure_translator.py
audioanalyser/modules/speech_text_server.py
audioanalyser/modules/text_to_speech.py
audioanalyser/modules/transcribe_audio_files.py
tests/__init__.py
audioanalyser-0.0.6.dist-info/LICENSE-APACHE
audioanalyser-0.0.6.dist-info/LICENSE-MIT
audioanalyser-0.0.6.dist-info/METADATA
audioanalyser-0.0.6.dist-info/WHEEL
audioanalyser-0.0.6.dist-info/top_level.txt
audioanalyser-0.0.6.dist-info/RECORD
