Metadata-Version: 2.1
Name: audioanalyser
Version: 0.0.6
Summary: Audio Analyser: Transform call recordings into actionable insights
Home-page: https://audioanalyser.co
Author: Sebastien Rousseau
Author-email: sebastian.rousseau@gmail.com
License: Apache Software License
Classifier: Development Status :: 4 - Beta
Classifier: Intended Audience :: Developers
Classifier: License :: OSI Approved :: MIT License
Classifier: Programming Language :: Python :: 3
Classifier: Programming Language :: Python :: 3.6
Classifier: Programming Language :: Python :: 3.7
Classifier: Programming Language :: Python :: 3.8
Classifier: Programming Language :: Python :: 3.9
Requires-Python: >=3.6
License-File: LICENSE-APACHE
License-File: LICENSE-MIT
Requires-Dist: azure-cognitiveservices-speech >=1.34.0
Requires-Dist: python-dotenv >=0.15.0
Requires-Dist: requests >=2.25.1
Requires-Dist: cherrypy >=18.6.0
